lamplight/chat_completion.py
lamplight-0.1.0.dist-info/LICENSE
lamplight-0.1.0.dist-info/METADATA
lamplight-0.1.0.dist-info/WHEEL
lamplight-0.1.0.dist-info/RECORD
